{
  "version": "6",
  "dialect": "sqlite",
  "id": "35500d53-9856-4ae4-a6ac-fdc55a07880c",
  "prevId": "00000000-0000-0000-0000-000000000000",
  "tables": {
    "reply_tracker": {
      "name": "reply_tracker",
      "columns": {
        "original_message_id": {
          "name": "original_message_id",
          "type": "text",
          "primaryKey": true,
          "notNull": true,
          "autoincrement": false
        },
        "reply_message_id": {
          "name": "reply_message_id",
          "type": "text",
          "primaryKey": false,
          "notNull": true,
          "autoincrement": false
        },
        "expires_at": {
          "name": "expires_at",
          "type": "integer",
          "primaryKey": false,
          "notNull": true,
          "autoincrement": false
        }
      },
      "indexes": {},
      "foreignKeys": {},
      "compositePrimaryKeys": {},
      "uniqueConstraints": {},
      "checkConstraints": {}
    },
    "server_config": {
      "name": "server_config",
      "columns": {
        "server_id": {
          "name": "server_id",
          "type": "text",
          "primaryKey": true,
          "notNull": true,
          "autoincrement": false
        },
        "config_json": {
          "name": "config_json",
          "type": "text",
          "primaryKey": false,
          "notNull": true,
          "autoincrement": false,
          "default": "'{}'"
        }
      },
      "indexes": {},
      "foreignKeys": {},
      "compositePrimaryKeys": {},
      "uniqueConstraints": {},
      "checkConstraints": {}
    }
  },
  "views": {},
  "enums": {},
  "_meta": {
    "schemas": {},
    "tables": {},
    "columns": {}
  },
  "internal": {
    "indexes": {}
  }
}